pyckagist/__init__.py
pyckagist/main.py
pyckagist/py.typed
pyckagist/api/__init__.py
pyckagist/api/interface.py
pyckagist/api/operator.py
pyckagist/api/source.py
pyckagist/core/__init__.py
pyckagist/core/context.py
pyckagist/core/controller.py
pyckagist/core/manager.py
pyckagist/core/remote.py
pyckagist/core/resolver.py
pyckagist/model/__init__.py
pyckagist/model/package.py
pyckagist/model/platform.py
pyckagist/model/remote.py
pyckagist/model/version.py
pyckagist/process/__init__.py
pyckagist/process/common.py
pyckagist/process/dispatcher.py
pyckagist/process/handle.py
pyckagist/registry/__init__.py
pyckagist/registry/operator.py
pyckagist/registry/package.py
pyckagist/registry/source.py
pyckagist/storage/__init__.py
pyckagist/storage/common.py
pyckagist/storage/manager.py
pyckagist/storage/entity/__init__.py
pyckagist/storage/entity/base.py
pyckagist/storage/entity/package.py
pyckagist/storage/entity/reference.py
pyckagist/storage/filesystem/__init__.py
pyckagist/storage/filesystem/manifest.py
pyckagist/storage/filesystem/storage.py
pyckagist-0.1.0.dist-info/METADATA
pyckagist-0.1.0.dist-info/WHEEL
pyckagist-0.1.0.dist-info/licenses/LICENSE
pyckagist-0.1.0.dist-info/RECORD
